Peertalk-0.1.5.dist-info/METADATA
Peertalk-0.1.5.dist-info/RECORD
Peertalk-0.1.5.dist-info/WHEEL
Peertalk-0.1.5.dist-info/top_level.txt
peertalk/__init__.py
peertalk/__main__.py
