Metadata-Version: 2.1
Name: Peertalk
Version: 0.1.5
Summary: An experimental, demonstrative chat protocol and implementation for use in Peertable networks
Home-page: UNKNOWN
Author: Gustavo6046
Author-email: gugurehermann@gmail.com
License: MIT
Keywords: p2p peer-to-peer peer network infrastructure chat test experimental protocol demo talk
Platform: UNKNOWN
Requires-Dist: wxpython (>=4.0.3)
Requires-Dist: peertable (>=0.1.3.4)
